fincalendar/__init__.py
fincalendar/currency_countrycode_mapping.py
fincalendar/equity_config.py
fincalendar/foreign_exchange_config.py
fincalendar/fx_settlement_date.py
fincalendar/holiday_mapping.py
fincalendar/holiday_overrides.py
fincalendar/holidays.py
fincalendar/settlement_cycle.py
fincalendar-0.1.5.dist-info/DESCRIPTION.rst
fincalendar-0.1.5.dist-info/METADATA
fincalendar-0.1.5.dist-info/RECORD
fincalendar-0.1.5.dist-info/WHEEL
fincalendar-0.1.5.dist-info/metadata.json
fincalendar-0.1.5.dist-info/top_level.txt
