Metadata-Version: 2.0
Name: fincalendar
Version: 0.1.5
Summary: Finance Calendar
Home-page: https://github.com/amaas-fintech/fincalendar
Author: AMaaS
Author-email: tech@amaas.com
License: Apache License 2.0
Platform: UNKNOWN
Classifier: Programming Language :: Python :: 2
Classifier: Programming Language :: Python :: 2.7
Classifier: Programming Language :: Python :: 3
Classifier: Programming Language :: Python :: 3.3
Classifier: Programming Language :: Python :: 3.4
Classifier: Programming Language :: Python :: 3.5
Classifier: Programming Language :: Python :: 3.6
Requires-Dist: python-dateutil
Requires-Dist: workalendar
Requires-Dist: pycountry
